<annotation>
    <folder>images</folder>
    <filename>DSCF1032_4_14.616.jpg</filename>
    <path>C:\Users\alons\PycharmProjects\keras-yolo2\create_annon_blur\busesTrain\images\DSCF1032_4_14.616.jpg</path>
    <source>
        <database>Unknown</database>
    </source>
    <size>
        <width>3648</width>
        <height>2736</height>
        <depth>3</depth>
    </size>
    <segmented>0</segmented>
    <object>
        <name>5</name>
        <pose>Unspecified</pose>
        <truncated>0</truncated>
        <difficult>0</difficult>
        <bndbox>
            <xmin>156</xmin>
            <ymin>1381</ymin>
            <xmax>1225</xmax>
            <ymax>2081</ymax>
        </bndbox>
    </object>    <object>
        <name>6</name>
        <pose>Unspecified</pose>
        <truncated>0</truncated>
        <difficult>0</difficult>
        <bndbox>
            <xmin>2261</xmin>
            <ymin>772</ymin>
            <xmax>3262</xmax>
            <ymax>1444</ymax>
        </bndbox>
    </object>
</annotation>
