<annotation>
    <folder>images</folder>
    <filename>DSCF1082_15_-8.65.jpg</filename>
    <path>C:\Users\alons\PycharmProjects\keras-yolo2\create_annon_blur\busesTrain\images\DSCF1082_15_-8.65.jpg</path>
    <source>
        <database>Unknown</database>
    </source>
    <size>
        <width>3648</width>
        <height>2736</height>
        <depth>3</depth>
    </size>
    <segmented>0</segmented>
    <object>
        <name>5</name>
        <pose>Unspecified</pose>
        <truncated>0</truncated>
        <difficult>0</difficult>
        <bndbox>
            <xmin>1044</xmin>
            <ymin>463</ymin>
            <xmax>2070</xmax>
            <ymax>1135</ymax>
        </bndbox>
    </object>    <object>
        <name>4</name>
        <pose>Unspecified</pose>
        <truncated>0</truncated>
        <difficult>0</difficult>
        <bndbox>
            <xmin>2149</xmin>
            <ymin>654</ymin>
            <xmax>3165</xmax>
            <ymax>1332</ymax>
        </bndbox>
    </object>
</annotation>
